README.md
setup.py
loc_tracker/__init__.py
loc_tracker/data_processing.py
loc_tracker/scoring.py
loc_tracker.egg-info/PKG-INFO
loc_tracker.egg-info/SOURCES.txt
loc_tracker.egg-info/dependency_links.txt
loc_tracker.egg-info/requires.txt
loc_tracker.egg-info/top_level.txt