Metadata-Version: 2.1
Name: loc_tracker
Version: 0.2
Summary: UAV data processing and scoring package
Home-page: https://github.com/0ea/loc_tracker
Author: Nurullah Eren
Author-email: n.erenacar13@gmail.com
Classifier: Programming Language :: Python :: 3
Classifier: License :: OSI Approved :: MIT License
Classifier: Operating System :: OS Independent
Requires-Python: >=3.6
Requires-Dist: geopy
Requires-Dist: shapely
